FoldOptLib/__init__.py
FoldOptLib/version.py
FoldOptLib/examples/__init__.py
FoldOptLib/examples/misc_functions.py
FoldOptLib/fold_modelling/__init__.py
FoldOptLib/fold_modelling/base_fold_frame_builder.py
FoldOptLib/fold_modelling/engine.py
FoldOptLib/fold_modelling/simple_fold_frame_builder.py
FoldOptLib/from_loopstructural/__init__.py
FoldOptLib/from_loopstructural/_fold.py
FoldOptLib/from_loopstructural/_fold_frame.py
FoldOptLib/from_loopstructural/_svariogram.py
FoldOptLib/helper/__init__.py
FoldOptLib/helper/_helper.py
FoldOptLib/helper/utils.py
FoldOptLib/input/__init__.py
FoldOptLib/input/input_data_checker.py
FoldOptLib/input/input_data_processor.py
FoldOptLib/ipywidgets_interface/__init__.py
FoldOptLib/ipywidgets_interface/knowledge_input.py
FoldOptLib/objective_functions/__init__.py
FoldOptLib/objective_functions/axial_plane.py
FoldOptLib/objective_functions/gaussian.py
FoldOptLib/objective_functions/geological_knowledge.py
FoldOptLib/objective_functions/lambda_objective_function.py
FoldOptLib/objective_functions/least_squares.py
FoldOptLib/objective_functions/von_mises_fisher.py
FoldOptLib/optimisers/__init__.py
FoldOptLib/optimisers/axial_surface_optimiser.py
FoldOptLib/optimisers/base_optimiser.py
FoldOptLib/optimisers/fold_optimiser.py
FoldOptLib/optimisers/fourier_optimiser.py
FoldOptLib/splot/__init__.py
FoldOptLib/splot/splot_processor.py
FoldOptLib/visualisation/__init__.py
FoldOptLib-0.1.6.dist-info/LICENSE
FoldOptLib-0.1.6.dist-info/METADATA
FoldOptLib-0.1.6.dist-info/WHEEL
FoldOptLib-0.1.6.dist-info/top_level.txt
FoldOptLib-0.1.6.dist-info/RECORD
